imathlogic/__init__.py
imathlogic/supervised/__init__.py
imathlogic-0.0.7.dist-info/LICENSE
imathlogic-0.0.7.dist-info/METADATA
imathlogic-0.0.7.dist-info/WHEEL
imathlogic-0.0.7.dist-info/top_level.txt
imathlogic-0.0.7.dist-info/RECORD
