Metadata-Version: 2.1
Name: imathlogic
Version: 0.0.7
Summary: Get the result of all types of algorithms in a simple way
Home-page: https://github.com/Sayan-Roy-729/iMathLogic
Author: Sayan Roy
Author-email: rsayan553@gmail.com
License: MIT
License-File: LICENSE
Requires-Dist: numpy
Requires-Dist: scikit-learn
Requires-Dist: pandas
Requires-Dist: tqdm
Requires-Dist: xgboost
